[
    {
        "id": "1",
        "type": "Fósforo(mg/dL)",
        "date": "07/23",
        "result": 4.5,
        "patientId": "1"
    },
    {
        "id": "2",
        "type": "Fósforo(mg/dL)",
        "date": "09/23",
        "result": 4,
        "patientId": "1"
    },
    {
        "id": "3",
        "type": "Fósforo(mg/dL)",
        "date": "01/24",
        "result": 5,
        "patientId": "1"
    },
    {
        "id": "4",
        "type": "Cálcio ionizado(mg/dL)",
        "date": "07/23",
        "result": 1.2,
        "patientId": "1"
    },
    {
        "id": "5",
        "type": "Cálcio ionizado(mg/dL)",
        "date": "09/23",
        "result": 1.1,
        "patientId": "1"
    },
    {
        "id": "6",
        "type": "Cálcio ionizado(mg/dL)",
        "date": "01/24",
        "result": 1.3,
        "patientId": "1"
    },
    {
        "id": "7",
        "type": "Pressão arterial(mmHg)",
        "date": "07/23",
        "result": 140,
        "patientId": "1"
    },
    {
        "id": "8",
        "type": "Pressão arterial(mmHg)",
        "date": "09/23",
        "result": 150,
        "patientId": "1"
    },
    {
        "id": "9",
        "type": "Pressão arterial(mmHg)",
        "date": "01/24",
        "result": 140,
        "patientId": "1"
    },
    {
        "id": "10",
        "type": "Ureia(mg/dL)",
        "date": "07/23",
        "result": 40,
        "patientId": "1"
    },
    {
        "id": "11",
        "type": "Ureia(mg/dL)",
        "date": "09/23",
        "result": 55,
        "patientId": "1"
    },
    {
        "id": "12",
        "type": "Ureia(mg/dL)",
        "date": "01/24",
        "result": 50,
        "patientId": "1"
    },
    {
        "id": "13",
        "type": "Creatinina",
        "date": "07/23",
        "result": 0.9,
        "patientId": "1"
    },
    {
        "id": "14",
        "type": "Creatinina",
        "date": "09/23",
        "result": 1.1,
        "patientId": "1"
    },
    {
        "id": "15",
        "type": "Creatinina",
        "date": "01/24",
        "result": 1,
        "patientId": "1"
    }
]